maskmark/__init__.py
maskmark/__version__.py
maskmark/api.py
maskmark/config.py
maskmark/default_rules.py
maskmark/core/mark.py
maskmark/core/mask.py
maskmark/engine/rule_engine.py
maskmark/font/SourceHanSansCN-Bold.otf
maskmark/font/SourceHanSansSC-VF.ttf
maskmark/service/interface.py
maskmark/service/mark_service.py
maskmark/service/mask_service.py
maskmark/utils/file.py
maskmark/utils/util.py
maskmark-0.1.3.dist-info/licenses/LICENSE
maskmark-0.1.3.dist-info/METADATA
maskmark-0.1.3.dist-info/WHEEL
maskmark-0.1.3.dist-info/top_level.txt
maskmark-0.1.3.dist-info/RECORD
