Metadata-Version: 2.4
Name: maskmark
Version: 0.1.3
Summary: 具备数据脱敏和数据水印功能的SDK包
Home-page: https://git.hl.hdkwst.space/handk/maskmarkSDK_py
Author: handk
Author-email: handk <handk5373@163.com>
License: GNU GENERAL PUBLIC LICENSE
Project-URL: Homepage, https://git.hl.hdkwst.space/handk/maskmarkSDK_py
Keywords: 数据脱敏,数据水印,SDK,mask,mark,data protection,security
Classifier: Programming Language :: Python :: 3
Classifier: Programming Language :: Python :: 3.7
Classifier: Programming Language :: Python :: 3.8
Classifier: Programming Language :: Python :: 3.9
Classifier: Programming Language :: Python :: 3.10
Classifier: Programming Language :: Python :: 3.11
Classifier: Programming Language :: Python :: 3.12
Classifier: Programming Language :: Python :: 3.13
Classifier: Programming Language :: Python :: 3 :: Only
Classifier: Operating System :: OS Independent
Requires-Python: >=3.7
License-File: LICENSE
Requires-Dist: pymupdf>=1.24.11
Requires-Dist: pillow>=10.4.0
Requires-Dist: filetype>=1.2.0
Requires-Dist: toml>=0.10.2
Requires-Dist: python-docx>=1.1.2
Requires-Dist: gmssl>=3.2.2
Dynamic: author
Dynamic: home-page
Dynamic: license-file
Dynamic: requires-python
